bote/__init__.py
bote/__main__.py
bote/_version.py
bote/err.py
bote/py.typed
bote-1.2.2.dist-info/LICENSE
bote-1.2.2.dist-info/METADATA
bote-1.2.2.dist-info/WHEEL
bote-1.2.2.dist-info/top_level.txt
bote-1.2.2.dist-info/RECORD
