Metadata-Version: 2.1
Name: bote
Version: 1.2.2
Summary: Send email messages and enforce encryption.
Home-page: https://github.com/RuedigerVoigt/bote
Author: Rüdiger Voigt
Author-email: projects@ruediger-voigt.eu
License: UNKNOWN
Platform: UNKNOWN
Classifier: Programming Language :: Python :: 3
Classifier: Programming Language :: Python :: 3.6
Classifier: Programming Language :: Python :: 3.7
Classifier: Programming Language :: Python :: 3.8
Classifier: Programming Language :: Python :: 3.9
Classifier: Programming Language :: Python :: 3.10
Classifier: License :: OSI Approved :: Apache Software License
Classifier: Operating System :: OS Independent
Classifier: Operating System :: POSIX :: Linux
Classifier: Operating System :: Microsoft :: Windows
Classifier: Operating System :: MacOS :: MacOS X
Classifier: Development Status :: 5 - Production/Stable
Classifier: Intended Audience :: Developers
Classifier: Topic :: System :: Monitoring
Classifier: Topic :: Communications :: Email
Classifier: Topic :: Security :: Cryptography
Requires-Python: >=3.6
Requires-Dist: compatibility (>=1.0.1)
Requires-Dist: userprovided (>=0.9.4)
